{
    "name": "13a-dark-alleys-compendium",
    "title": "13th Age Dark Alleys Compendium",
    "description": "Game rules & Compendiums for the 13th Age Compatible expansion book Dark Alleys & Twisted Path for Foundry Virtual Tabletop ",
    "version": "0.4.0",
    "minimumCoreVersion": "0.6.0",
    "compatibleCoreVersion": "0.7.9",
    "minimumSystemVersion": "1.5.0",
    "packs": [
        {
          "name": "clericspells",
          "label": "Dark Alleys Cleric Spells",
          "system": "archmage",
          "path": "./packs/dark-alleys-cleric-spells.db",
          "entity": "Item"
        },
		{
          "name": "wizardspells",
          "label": "Dark Alleys Wizard Spells",
          "system": "archmage",
          "path": "./packs/dark-alleys-wizard-spells.db",
          "entity": "Item"
        },
		{
          "name": "clericspells",
          "label": "Dark Alleys Sorcerer Spells",
          "system": "archmage",
          "path": "./packs/dark-alleys-sorcerer-spells.db",
          "entity": "Item"
        },
        {
          "name": "dark-alleys-barbarian",
          "label": "Dark Alleys Barbarian",
          "system": "archmage",
          "path": "./packs/dark-alleys-barbarian.db",
          "entity": "Item"
        },
        {
          "name": "dark-alleys-bard-features",
          "label": "Dark Alleys Bard Features",
          "system": "archmage",
          "path": "./packs/dark-alleys-bard-features.db",
          "entity": "Item"
        },
        {
          "name": "dark-alleys-fighter",
          "label": "Dark Alleys Fighter",
          "system": "archmage",
          "path": "./packs/dark-alleys-fighter.db",
          "entity": "Item"
        },
        {
          "name": "dark-alleys-necromancer-spells",
          "label": "Dark Alleys Necromancer Spells",
          "system": "archmage",
          "path": "./packs/dark-alleys-necromancer-spells.db",
          "entity": "Item"
        },
        {
          "name": "dark-alleys-occultist-spells",
          "label": "Dark Alleys Occultist Spells",
          "system": "archmage",
          "path": "./packs/dark-alleys-occultist-spells.db",
          "entity": "Item"
        }
    ],
    "manifest": "https://github.com/mk572/FoundryVTT-Dark-Alleys-Compendium/releases/download/latest/module.json",
    "download": "https://github.com/mk572/FoundryVTT-Dark-Alleys-Compendium/releases/download/latest/dark-alleys-compendium.zip"
}
